{
  "series": {
    "card_type": "Supremicus/HorizonTitleCard",
    "template_ids": [],
    "font_color": "rgb(4, 156, 220)",
    "font_vertical_shift": 452,
    "source_files": [
      "logo.png"
    ],
    "extras": {
      "episode_text_color": "white",
      "episode_text_font_size": "1.3",
      "episode_text_vertical_shift": "410",
      "h_align": "left",
      "symbol": "logo",
      "crt_overlay": "bezel"
    }
  },
  "episodes": {
    "s1e2": {
      "template_ids": [],
      "extras": {
        "h_align": "right"
      }
    },
    "s1e5": {
      "template_ids": [],
      "extras": {
        "h_align": "right"
      }
    },
    "s1e8": {
      "template_ids": [],
      "extras": {
        "h_align": "right"
      }
    },
    "s2e1": {
      "template_ids": [],
      "extras": {
        "h_align": "left"
      }
    },
    "s2e2": {
      "template_ids": [],
      "extras": {
        "h_align": "right"
      }
    },
    "s2e4": {
      "template_ids": [],
      "extras": {
        "h_align": "right"
      }
    },
    "s2e10": {
      "template_ids": [],
      "extras": {
        "h_align": "right"
      }
    }
  },
  "creator": "atabbott, IdiotTryingToFindWay",
  "description": [
    "Copied from IdiotTryingToFindWay's Blueprint with a corrected logo. Horizon card type using the Lumon logo."
  ],
  "previews": [
    "preview0.jpg",
    "preview1.jpg"
  ],
  "created": "2025-04-06T01:02:04"
}